[
  {
    "id": "color_damage",
    "name": "Цветной урон",
    "description": "Изменяет цвет сообщений урона в игре.",
    "version": "1.0",
    "size": "20 KB",
    "thumbnailFile": "preview.PNG"
  },
  {
    "id": "black_tree",
    "name": "Чёрные деревья",
    "description": "Заменяет текстуры деревьев на чёрные пики.",
    "version": "1.0",
    "size": "19.1 MB",
    "thumbnailFile": "preview.PNG"
  },
  {
    "id": "prist_animation",
    "name": "Анимации приста",
    "description": "Замена файлов анимации приста.",
    "version": "1.0",
    "size": "6.2 MB",
    "installMode": "game",
    "thumbnailFile": "preview.PNG"
  }
]